qa_metrics/RewardBert.py
qa_metrics/__init__.py
qa_metrics/answerBERT.py
qa_metrics/em.py
qa_metrics/f1.py
qa_metrics/pedant.py
qa_metrics/prompt_llm.py
qa_metrics/prompt_open_llm.py
qa_metrics/transformerMatcher.py
qa_metrics/utils/__init__.py
qa_metrics/utils/tools.py
qa_metrics-0.2.42.dist-info/licenses/LICENSE
qa_metrics-0.2.42.dist-info/METADATA
qa_metrics-0.2.42.dist-info/WHEEL
qa_metrics-0.2.42.dist-info/top_level.txt
qa_metrics-0.2.42.dist-info/RECORD
